duper/__init__.py
duper/analysis.py
duper/base.py
duper/helper.py
duper/generator/__init__.py
duper/generator/base.py
duper/generator/category.py
duper/generator/constant.py
duper/generator/quantile.py
duper/generator/regex.py
data_duper-0.1.1.dist-info/LICENSE
data_duper-0.1.1.dist-info/METADATA
data_duper-0.1.1.dist-info/WHEEL
data_duper-0.1.1.dist-info/top_level.txt
data_duper-0.1.1.dist-info/RECORD
