Metadata-Version: 2.1
Name: data-duper
Version: 0.1.1
Summary: Replicate structure of private or protected data for testing.
Home-page: https://github.com/kjanker/data-duper
Author: Kevin Anker
License: MIT
Keywords: duper,data,testing
Platform: UNKNOWN
Classifier: Programming Language :: Python :: 3
Classifier: License :: OSI Approved :: MIT License
Classifier: Operating System :: OS Independent
Requires-Python: >=3.8
License-File: LICENSE
Requires-Dist: numpy (>=1.21.0)
Requires-Dist: pandas (>=1.1.0)
Requires-Dist: rstr (>=2.2.6)
